{"ConsultaInfoEmp":{"Nome de Pregão":"KLABIN S/A","Atividade Principal":"Empresa Brasileira de Base Florestal. Produtora de Papéis E Cartões Para Embalagens. Embalagens de Papelão Ondulado E Sacos Industriais. Além de Ser Recicladora E Produtora de Toras Para Serrarias.","Classificação Setorial":"Materiais Básicos / Madeira e Papel / Papel e Celulose","Site":"www.klabin.com.br","Códigos de Negociação":["KLBN11","KLBN3","KLBN4"]},"dfps":[{"ComposicaoCapitalSocial":{"QuantidadeAcaoOrdinariaCapitalIntegralizado":"1849270515","QuantidadeAcaoPreferencialCapitalIntegralizado":"2883910625","QuantidadeTotalAcaoCapitalIntegralizado":"4733181140"},"Documento":{"CompanhiaAberta":{"NumeroSequencialRegistroCvm":"4009","CodigoTipoParticipante":"1","CodigoCvm":"012653","IndicadorSociedadeAnonimaAtiva":"true","TemIPE":"false","NomeRazaoSocialCompanhiaAberta":"KLABIN S.A.","NumeroCnpjCompanhiaAberta":"89637490000145","CodigoCategoriaEmissor":"1","CodigoSituacaoRegistroCvm":"1","CodigoSituacaoCompanhiaAberta":"2","NumeroMesEncerramentoExercicioSocial":"0","NumeroAnoEncerramentoExercicioSocial":"0","TipoEmpresa":"0","DataRegistroCvm":"1997-08-06T00:00:00","DataInicioRazaoSocial":"0001-01-01T00:00:00","DataConstituicaoEmpresa":"1978-11-08T00:00:00","DataInicioSituacaoCompanhiaAberta":"1997-08-06T00:00:00","DataInicioSituacaoRegistroCvm":"1997-08-06T00:00:00","CodigoSetorAtividadeEmpresa":"1040","CodigoEspecieControleAcionario":"5","DataUltimaAlteracaoControleAcionario":"0001-01-01T00:00:00","DataRegistroAtualCategoriaEmissorCvm":"2010-01-01T00:00:00"},"DataReferenciaDocumento":"2016","CodigoEscalaQuantidade":"1"},"PagamentoProventoDinheiro":[{"EventoOrigemProvento":"Reunião do Conselho de Administração","DataAprovacaoProvento":"2016-02-02","TipoProvento":"Dividendo","DataInicioPagamento":"2016-02-22","CodigoEspecieAcao":"ON","CodigoClasseAcaoPreferencial":{},"ValorProventoPorAcao":"0.0262100000"},{"EventoOrigemProvento":"Reunião do Conselho de Administração","DataAprovacaoProvento":"2016-02-02","TipoProvento":"Dividendo","DataInicioPagamento":"2016-02-22","CodigoEspecieAcao":"PN","CodigoClasseAcaoPreferencial":{},"ValorProventoPorAcao":"0.0262100000"},{"EventoOrigemProvento":"Reunião do Conselho de Administração","DataAprovacaoProvento":"2016-04-28","TipoProvento":"Dividendo","DataInicioPagamento":"2016-05-11","CodigoEspecieAcao":"ON","CodigoClasseAcaoPreferencial":{},"ValorProventoPorAcao":"0.0223700000"},{"EventoOrigemProvento":"Reunião do Conselho de Administração","DataAprovacaoProvento":"2016-04-28","TipoProvento":"Dividendo","DataInicioPagamento":"2016-05-11","CodigoEspecieAcao":"PN","CodigoClasseAcaoPreferencial":{},"ValorProventoPorAcao":"0.0223700000"},{"EventoOrigemProvento":"Reunião do Conselho de Administração","DataAprovacaoProvento":"2016-07-26","TipoProvento":"Dividendo","DataInicioPagamento":"2016-08-10","CodigoEspecieAcao":"ON","CodigoClasseAcaoPreferencial":{},"ValorProventoPorAcao":"0.0235800000"},{"EventoOrigemProvento":"Reunião do Conselho de Administração","DataAprovacaoProvento":"2016-07-26","TipoProvento":"Dividendo","DataInicioPagamento":"2016-08-10","CodigoEspecieAcao":"PN","CodigoClasseAcaoPreferencial":{},"ValorProventoPorAcao":"0.0235800000"}],"XmlCode":"62409"},{"ComposicaoCapitalSocial":{"QuantidadeAcaoOrdinariaCapitalIntegralizado":"1849160105","QuantidadeAcaoPreferencialCapitalIntegralizado":"2883468985","QuantidadeTotalAcaoCapitalIntegralizado":"4732629090"},"Documento":{"CompanhiaAberta":{"NumeroSequencialRegistroCvm":"4009","CodigoTipoParticipante":"1","CodigoCvm":"012653","IndicadorSociedadeAnonimaAtiva":"true","TemIPE":"false","NomeRazaoSocialCompanhiaAberta":"KLABIN S.A.","NumeroCnpjCompanhiaAberta":"89637490000145","CodigoCategoriaEmissor":"1","CodigoSituacaoRegistroCvm":"1","CodigoSituacaoCompanhiaAberta":"2","NumeroMesEncerramentoExercicioSocial":"0","NumeroAnoEncerramentoExercicioSocial":"0","TipoEmpresa":"0","DataRegistroCvm":"1997-08-06T00:00:00","DataInicioRazaoSocial":"0001-01-01T00:00:00","DataConstituicaoEmpresa":"1978-11-08T00:00:00","DataInicioSituacaoCompanhiaAberta":"1997-08-06T00:00:00","DataInicioSituacaoRegistroCvm":"1997-08-06T00:00:00","CodigoSetorAtividadeEmpresa":"1040","CodigoEspecieControleAcionario":"5","DataUltimaAlteracaoControleAcionario":"0001-01-01T00:00:00","DataRegistroAtualCategoriaEmissorCvm":"2010-01-01T00:00:00"},"DataReferenciaDocumento":"2015","CodigoEscalaQuantidade":"1"},"PagamentoProventoDinheiro":[{"EventoOrigemProvento":"Assembléia Geral Ordinária e Extraordinária","DataAprovacaoProvento":"2015-03-19","TipoProvento":"Dividendo","DataInicioPagamento":"2015-04-06","CodigoEspecieAcao":"ON","CodigoClasseAcaoPreferencial":{},"ValorProventoPorAcao":"0.0222700000"},{"EventoOrigemProvento":"Assembléia Geral Ordinária e Extraordinária","DataAprovacaoProvento":"2015-03-19","TipoProvento":"Dividendo","DataInicioPagamento":"2015-04-06","CodigoEspecieAcao":"PN","CodigoClasseAcaoPreferencial":{},"ValorProventoPorAcao":"0.0222700000"},{"EventoOrigemProvento":"Reunião do Conselho de Administração","DataAprovacaoProvento":"2015-07-24","TipoProvento":"Dividendo","DataInicioPagamento":"2015-08-07","CodigoEspecieAcao":"ON","CodigoClasseAcaoPreferencial":{},"ValorProventoPorAcao":"0.0373400000"},{"EventoOrigemProvento":"Reunião do Conselho de Administração","DataAprovacaoProvento":"2015-07-24","TipoProvento":"Dividendo","DataInicioPagamento":"2015-08-07","CodigoEspecieAcao":"PN","CodigoClasseAcaoPreferencial":{},"ValorProventoPorAcao":"0.0373400000"},{"EventoOrigemProvento":"Reunião do Conselho de Administração","DataAprovacaoProvento":"2015-10-26","TipoProvento":"Dividendo","DataInicioPagamento":"2015-11-09","CodigoEspecieAcao":"ON","CodigoClasseAcaoPreferencial":{},"ValorProventoPorAcao":"0.0229300000"},{"EventoOrigemProvento":"Reunião do Conselho de Administração","DataAprovacaoProvento":"2015-10-26","TipoProvento":"Dividendo","DataInicioPagamento":"2015-11-09","CodigoEspecieAcao":"PN","CodigoClasseAcaoPreferencial":{},"ValorProventoPorAcao":"0.0229300000"}],"XmlCode":"53175"},{"ComposicaoCapitalSocial":{"QuantidadeAcaoOrdinariaCapitalIntegralizado":"1848592200","QuantidadeAcaoPreferencialCapitalIntegralizado":"2881197365","QuantidadeTotalAcaoCapitalIntegralizado":"4729789565"},"Documento":{"CompanhiaAberta":{"NumeroSequencialRegistroCvm":"4009","CodigoTipoParticipante":"1","CodigoCvm":"012653","IndicadorSociedadeAnonimaAtiva":"true","NomeRazaoSocialCompanhiaAberta":"KLABIN S.A.","NumeroCnpjCompanhiaAberta":"89637490000145","CodigoCategoriaEmissor":"1","CodigoSituacaoRegistroCvm":"1","CodigoSituacaoCompanhiaAberta":"2","NumeroMesEncerramentoExercicioSocial":"0","NumeroAnoEncerramentoExercicioSocial":"0","TipoEmpresa":"0","DataRegistroCvm":"1997-08-06T00:00:00","DataInicioRazaoSocial":"0001-01-01T00:00:00","DataConstituicaoEmpresa":"1978-11-08T00:00:00","DataInicioSituacaoCompanhiaAberta":"1997-08-06T00:00:00","DataInicioSituacaoRegistroCvm":"1997-08-06T00:00:00","CodigoSetorAtividadeEmpresa":"1040","CodigoEspecieControleAcionario":"5","DataUltimaAlteracaoControleAcionario":"0001-01-01T00:00:00","DataRegistroAtualCategoriaEmissorCvm":"2010-01-01T00:00:00"},"DataReferenciaDocumento":"2014","CodigoEscalaQuantidade":"1"},"PagamentoProventoDinheiro":[{"EventoOrigemProvento":"Assembléia Geral Ordinária e Extraordinária","DataAprovacaoProvento":"2014-03-20","TipoProvento":"Dividendo","DataInicioPagamento":"2014-04-09","CodigoEspecieAcao":"ON","CodigoClasseAcaoPreferencial":{},"ValorProventoPorAcao":"0.0952000000"},{"EventoOrigemProvento":"Assembléia Geral Ordinária e Extraordinária","DataAprovacaoProvento":"2014-03-20","TipoProvento":"Dividendo","DataInicioPagamento":"2014-04-09","CodigoEspecieAcao":"PN","CodigoClasseAcaoPreferencial":{},"ValorProventoPorAcao":"0.0952000000"},{"EventoOrigemProvento":"Reunião do Conselho de Administração","DataAprovacaoProvento":"2014-07-30","TipoProvento":"Dividendo","DataInicioPagamento":"2014-08-20","CodigoEspecieAcao":"ON","CodigoClasseAcaoPreferencial":{},"ValorProventoPorAcao":"0.0331800000"},{"EventoOrigemProvento":"Reunião do Conselho de Administração","DataAprovacaoProvento":"2014-07-30","TipoProvento":"Dividendo","DataInicioPagamento":"2014-08-20","CodigoEspecieAcao":"PN","CodigoClasseAcaoPreferencial":{},"ValorProventoPorAcao":"0.0331800000"},{"EventoOrigemProvento":"Reunião do Conselho de Administração","DataAprovacaoProvento":"2014-10-29","TipoProvento":"Dividendo","DataInicioPagamento":"2014-11-19","CodigoEspecieAcao":"ON","CodigoClasseAcaoPreferencial":{},"ValorProventoPorAcao":"0.0196500000"},{"EventoOrigemProvento":"Reunião do Conselho de Administração","DataAprovacaoProvento":"2014-10-29","TipoProvento":"Dividendo","DataInicioPagamento":"2014-11-19","CodigoEspecieAcao":"PN","CodigoClasseAcaoPreferencial":{},"ValorProventoPorAcao":"0.0196500000"}],"XmlCode":"43996"},{"ComposicaoCapitalSocial":{"QuantidadeAcaoOrdinariaCapitalIntegralizado":"316827563","QuantidadeAcaoPreferencialCapitalIntegralizado":"600855733","QuantidadeTotalAcaoCapitalIntegralizado":"917683296"},"Documento":{"CompanhiaAberta":{"NumeroSequencialRegistroCvm":"4009","CodigoTipoParticipante":"1","CodigoCvm":"012653","IndicadorSociedadeAnonimaAtiva":"true","NomeRazaoSocialCompanhiaAberta":"KLABIN S.A.","NumeroCnpjCompanhiaAberta":"89637490000145","CodigoCategoriaEmissor":"1","CodigoSituacaoRegistroCvm":"1","CodigoSituacaoCompanhiaAberta":"2","NumeroMesEncerramentoExercicioSocial":"0","NumeroAnoEncerramentoExercicioSocial":"0","TipoEmpresa":"0","DataRegistroCvm":"1997-08-06T00:00:00","DataInicioRazaoSocial":"0001-01-01T00:00:00","DataConstituicaoEmpresa":"1978-11-08T00:00:00","DataInicioSituacaoCompanhiaAberta":"1997-08-06T00:00:00","DataInicioSituacaoRegistroCvm":"1997-08-06T00:00:00","CodigoSetorAtividadeEmpresa":"1040","CodigoEspecieControleAcionario":"5","DataUltimaAlteracaoControleAcionario":"0001-01-01T00:00:00","DataRegistroAtualCategoriaEmissorCvm":"2010-01-01T00:00:00"},"DataReferenciaDocumento":"2013","CodigoEscalaQuantidade":"1"},"PagamentoProventoDinheiro":[{"EventoOrigemProvento":"Assembléia Geral Ordinária","DataAprovacaoProvento":"2013-04-02","TipoProvento":"Dividendo","DataInicioPagamento":"2013-04-23","CodigoEspecieAcao":"ON","CodigoClasseAcaoPreferencial":{},"ValorProventoPorAcao":"0.0805200000"},{"EventoOrigemProvento":"Assembléia Geral Ordinária","DataAprovacaoProvento":"2013-04-02","TipoProvento":"Dividendo","DataInicioPagamento":"2013-04-23","CodigoEspecieAcao":"PN","CodigoClasseAcaoPreferencial":{},"ValorProventoPorAcao":"0.0885700000"},{"EventoOrigemProvento":"Reunião do Conselho de Administração","DataAprovacaoProvento":"2013-07-25","TipoProvento":"Dividendo","DataInicioPagamento":"2013-08-15","CodigoEspecieAcao":"ON","CodigoClasseAcaoPreferencial":{},"ValorProventoPorAcao":"0.1482100000"},{"EventoOrigemProvento":"Reunião do Conselho de Administração","DataAprovacaoProvento":"2013-07-25","TipoProvento":"Dividendo","DataInicioPagamento":"2013-08-15","CodigoEspecieAcao":"PN","CodigoClasseAcaoPreferencial":{},"ValorProventoPorAcao":"0.1630300000"},{"EventoOrigemProvento":"Reunião do Conselho de Administração","DataAprovacaoProvento":"2013-10-30","TipoProvento":"Dividendo","DataInicioPagamento":"2013-11-22","CodigoEspecieAcao":"ON","CodigoClasseAcaoPreferencial":{},"ValorProventoPorAcao":"0.0899800000"},{"EventoOrigemProvento":"Reunião do Conselho de Administração","DataAprovacaoProvento":"2013-10-30","TipoProvento":"Dividendo","DataInicioPagamento":"2013-11-22","CodigoEspecieAcao":"PN","CodigoClasseAcaoPreferencial":{},"ValorProventoPorAcao":"0.0989800000"}],"XmlCode":"34485"},{"ComposicaoCapitalSocial":{"QuantidadeAcaoOrdinariaCapitalIntegralizado":"316827563","QuantidadeAcaoPreferencialCapitalIntegralizado":"600855733","QuantidadeTotalAcaoCapitalIntegralizado":"917683296"},"Documento":{"CompanhiaAberta":{"NumeroSequencialRegistroCvm":"4009","CodigoTipoParticipante":"1","CodigoCvm":"012653","IndicadorSociedadeAnonimaAtiva":"true","NomeRazaoSocialCompanhiaAberta":"KLABIN S.A.","NumeroCnpjCompanhiaAberta":"89637490000145","CodigoCategoriaEmissor":"1","CodigoSituacaoRegistroCvm":"1","CodigoSituacaoCompanhiaAberta":"2","NumeroMesEncerramentoExercicioSocial":"0","NumeroAnoEncerramentoExercicioSocial":"0","TipoEmpresa":"0","DataRegistroCvm":"1997-08-06T00:00:00","DataInicioRazaoSocial":"0001-01-01T00:00:00","DataConstituicaoEmpresa":"1978-11-08T00:00:00","DataInicioSituacaoCompanhiaAberta":"1997-08-06T00:00:00","DataInicioSituacaoRegistroCvm":"1997-08-06T00:00:00","CodigoSetorAtividadeEmpresa":"1040","CodigoEspecieControleAcionario":"5","DataUltimaAlteracaoControleAcionario":"0001-01-01T00:00:00","DataRegistroAtualCategoriaEmissorCvm":"2010-01-01T00:00:00"},"DataReferenciaDocumento":"2012","CodigoEscalaQuantidade":"1"},"PagamentoProventoDinheiro":[{"EventoOrigemProvento":"Assembléia Geral Ordinária","DataAprovacaoProvento":"2012-04-03","TipoProvento":"Dividendo","DataInicioPagamento":"2012-04-23","CodigoEspecieAcao":"ON","CodigoClasseAcaoPreferencial":{},"ValorProventoPorAcao":"0.0847400000"},{"EventoOrigemProvento":"Assembléia Geral Ordinária","DataAprovacaoProvento":"2012-04-03","TipoProvento":"Dividendo","DataInicioPagamento":"2012-04-23","CodigoEspecieAcao":"PN","CodigoClasseAcaoPreferencial":{},"ValorProventoPorAcao":"0.0932600000"},{"EventoOrigemProvento":"Reunião do Conselho de Administração","DataAprovacaoProvento":"2012-06-27","TipoProvento":"Dividendo","DataInicioPagamento":"2012-07-19","CodigoEspecieAcao":"ON","CodigoClasseAcaoPreferencial":{},"ValorProventoPorAcao":"0.1270200000"},{"EventoOrigemProvento":"Reunião do Conselho de Administração","DataAprovacaoProvento":"2012-06-27","TipoProvento":"Dividendo","DataInicioPagamento":"2012-07-19","CodigoEspecieAcao":"PN","CodigoClasseAcaoPreferencial":{},"ValorProventoPorAcao":"0.1397200000"},{"EventoOrigemProvento":"Reunião do Conselho de Administração","DataAprovacaoProvento":"2012-10-26","TipoProvento":"Dividendo","DataInicioPagamento":"2012-11-21","CodigoEspecieAcao":"ON","CodigoClasseAcaoPreferencial":{},"ValorProventoPorAcao":"0.0793900000"},{"EventoOrigemProvento":"Reunião do Conselho de Administração","DataAprovacaoProvento":"2012-10-26","TipoProvento":"Dividendo","DataInicioPagamento":"2012-11-21","CodigoEspecieAcao":"PN","CodigoClasseAcaoPreferencial":{},"ValorProventoPorAcao":"0.0873300000"},{"EventoOrigemProvento":"Proposta","DataAprovacaoProvento":"0001-01-01","TipoProvento":"Dividendo","DataInicioPagamento":"0001-01-01","CodigoEspecieAcao":"ON","CodigoClasseAcaoPreferencial":{},"ValorProventoPorAcao":"0.0805200000"},{"EventoOrigemProvento":"Proposta","DataAprovacaoProvento":"0001-01-01","TipoProvento":"Dividendo","DataInicioPagamento":"0001-01-01","CodigoEspecieAcao":"PN","CodigoClasseAcaoPreferencial":{},"ValorProventoPorAcao":"0.0885700000"}],"XmlCode":"24397"},{"ComposicaoCapitalSocial":{"QuantidadeAcaoOrdinariaCapitalIntegralizado":"316827563","QuantidadeAcaoPreferencialCapitalIntegralizado":"600855733","QuantidadeTotalAcaoCapitalIntegralizado":"917683296"},"Documento":{"CompanhiaAberta":{"NumeroSequencialRegistroCvm":"4009","CodigoTipoParticipante":"1","CodigoCvm":"012653","IndicadorSociedadeAnonimaAtiva":"true","NomeRazaoSocialCompanhiaAberta":"KLABIN S.A.","NumeroCnpjCompanhiaAberta":"89637490000145","CodigoCategoriaEmissor":"1","CodigoSituacaoRegistroCvm":"1","CodigoSituacaoCompanhiaAberta":"2","NumeroMesEncerramentoExercicioSocial":"0","NumeroAnoEncerramentoExercicioSocial":"0","TipoEmpresa":"0","DataRegistroCvm":"1997-08-06T00:00:00","DataInicioRazaoSocial":"0001-01-01T00:00:00","DataConstituicaoEmpresa":"1978-11-08T00:00:00","DataInicioSituacaoCompanhiaAberta":"1997-08-06T00:00:00","DataInicioSituacaoRegistroCvm":"1997-08-06T00:00:00","CodigoSetorAtividadeEmpresa":"1040","CodigoEspecieControleAcionario":"5","DataUltimaAlteracaoControleAcionario":"0001-01-01T00:00:00","DataRegistroAtualCategoriaEmissorCvm":"2010-01-01T00:00:00"},"DataReferenciaDocumento":"2011","CodigoEscalaQuantidade":"1"},"PagamentoProventoDinheiro":[{"EventoOrigemProvento":"Assembléia Geral Ordinária","DataAprovacaoProvento":"2011-04-04","TipoProvento":"Dividendo","DataInicioPagamento":"2011-04-20","CodigoEspecieAcao":"ON","CodigoClasseAcaoPreferencial":{},"ValorProventoPorAcao":"0.0738500000"},{"EventoOrigemProvento":"Assembléia Geral Ordinária","DataAprovacaoProvento":"2011-04-04","TipoProvento":"Dividendo","DataInicioPagamento":"2011-04-20","CodigoEspecieAcao":"PN","CodigoClasseAcaoPreferencial":{},"ValorProventoPorAcao":"0.0812400000"},{"EventoOrigemProvento":"Reunião do Conselho de Administração","DataAprovacaoProvento":"2011-06-21","TipoProvento":"Dividendo","DataInicioPagamento":"2011-07-15","CodigoEspecieAcao":"ON","CodigoClasseAcaoPreferencial":{},"ValorProventoPorAcao":"0.0865100000"},{"EventoOrigemProvento":"Reunião do Conselho de Administração","DataAprovacaoProvento":"2011-06-21","TipoProvento":"Dividendo","DataInicioPagamento":"2011-07-15","CodigoEspecieAcao":"PN","CodigoClasseAcaoPreferencial":{},"ValorProventoPorAcao":"0.0951600000"},{"EventoOrigemProvento":"Reunião do Conselho de Administração","DataAprovacaoProvento":"2011-09-22","TipoProvento":"Dividendo","DataInicioPagamento":"2011-10-11","CodigoEspecieAcao":"ON","CodigoClasseAcaoPreferencial":{},"ValorProventoPorAcao":"0.0582200000"},{"EventoOrigemProvento":"Reunião do Conselho de Administração","DataAprovacaoProvento":"2011-09-22","TipoProvento":"Dividendo","DataInicioPagamento":"2011-10-11","CodigoEspecieAcao":"PN","CodigoClasseAcaoPreferencial":{},"ValorProventoPorAcao":"0.0640400000"},{"EventoOrigemProvento":"Proposta","DataAprovacaoProvento":"0001-01-01","TipoProvento":"Dividendo","DataInicioPagamento":"0001-01-01","CodigoEspecieAcao":"ON","CodigoClasseAcaoPreferencial":{},"ValorProventoPorAcao":"0.0847400000"},{"EventoOrigemProvento":"Proposta","DataAprovacaoProvento":"0001-01-01","TipoProvento":"Dividendo","DataInicioPagamento":"0001-01-01","CodigoEspecieAcao":"PN","CodigoClasseAcaoPreferencial":{},"ValorProventoPorAcao":"0.0932100000"}],"XmlCode":"14625"},{"ComposicaoCapitalSocial":{"QuantidadeAcaoOrdinariaCapitalIntegralizado":"316827563","QuantidadeAcaoPreferencialCapitalIntegralizado":"600855733","QuantidadeTotalAcaoCapitalIntegralizado":"917683296"},"Documento":{"CompanhiaAberta":{"NumeroSequencialRegistroCvm":"4009","CodigoTipoParticipante":"1","CodigoCvm":"012653","IndicadorSociedadeAnonimaAtiva":"true","NomeRazaoSocialCompanhiaAberta":"KLABIN S.A.","NumeroCnpjCompanhiaAberta":"89637490000145","CodigoCategoriaEmissor":"1","CodigoSituacaoRegistroCvm":"1","CodigoSituacaoCompanhiaAberta":"2","NumeroMesEncerramentoExercicioSocial":"0","NumeroAnoEncerramentoExercicioSocial":"0","TipoEmpresa":"0","DataRegistroCvm":"1997-08-06T00:00:00","DataInicioRazaoSocial":"0001-01-01T00:00:00","DataConstituicaoEmpresa":"1978-11-08T00:00:00","DataInicioSituacaoCompanhiaAberta":"1997-08-06T00:00:00","DataInicioSituacaoRegistroCvm":"1997-08-06T00:00:00","CodigoSetorAtividadeEmpresa":"1040","CodigoEspecieControleAcionario":"5","DataUltimaAlteracaoControleAcionario":"0001-01-01T00:00:00","DataRegistroAtualCategoriaEmissorCvm":"2010-01-01T00:00:00"},"DataReferenciaDocumento":"2010","CodigoEscalaQuantidade":"1"},"PagamentoProventoDinheiro":[{"EventoOrigemProvento":"Reunião do Conselho de Administração","DataAprovacaoProvento":"2010-07-05","TipoProvento":"Dividendo","DataInicioPagamento":"2010-07-20","CodigoEspecieAcao":"ON","CodigoClasseAcaoPreferencial":{},"ValorProventoPorAcao":"0.0521300000"},{"EventoOrigemProvento":"Reunião do Conselho de Administração","DataAprovacaoProvento":"2010-07-05","TipoProvento":"Dividendo","DataInicioPagamento":"2010-07-20","CodigoEspecieAcao":"PN","CodigoClasseAcaoPreferencial":{},"ValorProventoPorAcao":"0.0573400000"},{"EventoOrigemProvento":"Reunião do Conselho de Administração","DataAprovacaoProvento":"2010-09-21","TipoProvento":"Dividendo","DataInicioPagamento":"2010-10-08","CodigoEspecieAcao":"ON","CodigoClasseAcaoPreferencial":{},"ValorProventoPorAcao":"0.0729800000"},{"EventoOrigemProvento":"Reunião do Conselho de Administração","DataAprovacaoProvento":"2010-09-21","TipoProvento":"Dividendo","DataInicioPagamento":"2010-10-08","CodigoEspecieAcao":"PN","CodigoClasseAcaoPreferencial":{},"ValorProventoPorAcao":"0.0802800000"},{"EventoOrigemProvento":"Proposta","DataAprovacaoProvento":"0001-01-01","TipoProvento":"Dividendo","DataInicioPagamento":"0001-01-01","CodigoEspecieAcao":"ON","CodigoClasseAcaoPreferencial":{},"ValorProventoPorAcao":"0.0729800000"},{"EventoOrigemProvento":"Proposta","DataAprovacaoProvento":"0001-01-01","TipoProvento":"Dividendo","DataInicioPagamento":"0001-01-01","CodigoEspecieAcao":"PN","CodigoClasseAcaoPreferencial":{},"ValorProventoPorAcao":"0.0802800000"}],"XmlCode":"4933"}]}