{"ConsultaInfoEmp":{"Nome de Pregão":"M.DIASBRANCO","Atividade Principal":"Produção E Comercialização de Biscoitos. Massas. Farinha de Trigo E Farelo. Margarinas E Gorduras. Bolos. Snacks. Mistura Para Bolos E Torradas.","Classificação Setorial":"Consumo não Cíclico / Alimentos Processados / Alimentos Diversos","Site":"www.mdiasbranco.com.br","Códigos de Negociação":["MDIA3"]},"dfps":[{"ComposicaoCapitalSocial":{"QuantidadeAcaoOrdinariaCapitalIntegralizado":"113000000","QuantidadeAcaoPreferencialCapitalIntegralizado":"0","QuantidadeTotalAcaoCapitalIntegralizado":"113000000"},"Documento":{"CompanhiaAberta":{"NumeroSequencialRegistroCvm":"3630","CodigoTipoParticipante":"1","CodigoCvm":"020338","IndicadorSociedadeAnonimaAtiva":"true","TemIPE":"false","NomeRazaoSocialCompanhiaAberta":"M DIAS BRANCO SA IND E COM DE ALIMENTOS","NumeroCnpjCompanhiaAberta":"07206816000115","CodigoCategoriaEmissor":"1","CodigoSituacaoRegistroCvm":"1","CodigoSituacaoCompanhiaAberta":"2","NumeroMesEncerramentoExercicioSocial":"0","NumeroAnoEncerramentoExercicioSocial":"0","TipoEmpresa":"0","DataRegistroCvm":"2006-10-11T00:00:00","DataInicioRazaoSocial":"0001-01-01T00:00:00","DataConstituicaoEmpresa":"1961-01-01T00:00:00","DataInicioSituacaoCompanhiaAberta":"2006-10-11T00:00:00","DataInicioSituacaoRegistroCvm":"2006-10-11T00:00:00","CodigoSetorAtividadeEmpresa":"1220","CodigoEspecieControleAcionario":"5","DataUltimaAlteracaoControleAcionario":"0001-01-01T00:00:00","DataRegistroAtualCategoriaEmissorCvm":"2010-01-01T00:00:00"},"DataReferenciaDocumento":"2016","CodigoEscalaQuantidade":"1"},"PagamentoProventoDinheiro":[{"EventoOrigemProvento":"Assembléia Geral Ordinária e Extraordinária","DataAprovacaoProvento":"2016-04-11","TipoProvento":"Juros sobre Capital Próprio","DataInicioPagamento":"2016-04-25","CodigoEspecieAcao":"ON","CodigoClasseAcaoPreferencial":{},"ValorProventoPorAcao":"0.7200000000"},{"EventoOrigemProvento":"Reunião do Conselho de Administração","DataAprovacaoProvento":"2016-08-01","TipoProvento":"Juros sobre Capital Próprio","DataInicioPagamento":"2016-08-16","CodigoEspecieAcao":"ON","CodigoClasseAcaoPreferencial":{},"ValorProventoPorAcao":"0.5000000000"},{"EventoOrigemProvento":"Reunião do Conselho de Administração","DataAprovacaoProvento":"2016-12-12","TipoProvento":"Juros sobre Capital Próprio","DataInicioPagamento":"2017-04-28","CodigoEspecieAcao":"ON","CodigoClasseAcaoPreferencial":{},"ValorProventoPorAcao":"1.0500000000"}],"XmlCode":"62917"},{"ComposicaoCapitalSocial":{"QuantidadeAcaoOrdinariaCapitalIntegralizado":"113000000","QuantidadeAcaoPreferencialCapitalIntegralizado":"0","QuantidadeTotalAcaoCapitalIntegralizado":"113000000"},"Documento":{"CompanhiaAberta":{"NumeroSequencialRegistroCvm":"3630","CodigoTipoParticipante":"1","CodigoCvm":"020338","IndicadorSociedadeAnonimaAtiva":"true","TemIPE":"false","NomeRazaoSocialCompanhiaAberta":"M DIAS BRANCO SA IND E COM DE ALIMENTOS","NumeroCnpjCompanhiaAberta":"07206816000115","CodigoCategoriaEmissor":"1","CodigoSituacaoRegistroCvm":"1","CodigoSituacaoCompanhiaAberta":"2","NumeroMesEncerramentoExercicioSocial":"0","NumeroAnoEncerramentoExercicioSocial":"0","TipoEmpresa":"1","DataRegistroCvm":"2006-10-11T00:00:00","DataInicioRazaoSocial":"0001-01-01T00:00:00","DataConstituicaoEmpresa":"1961-01-01T00:00:00","DataInicioSituacaoCompanhiaAberta":"2006-10-11T00:00:00","DataInicioSituacaoRegistroCvm":"2006-10-11T00:00:00","CodigoSetorAtividadeEmpresa":"1220","CodigoEspecieControleAcionario":"5","DataUltimaAlteracaoControleAcionario":"0001-01-01T00:00:00","DataRegistroAtualCategoriaEmissorCvm":"2010-01-01T00:00:00"},"DataReferenciaDocumento":"2015","CodigoEscalaQuantidade":"1"},"PagamentoProventoDinheiro":[{"EventoOrigemProvento":"Reunião do Conselho de Administração","DataAprovacaoProvento":"2015-12-14","TipoProvento":"Juros sobre Capital Próprio","DataInicioPagamento":"2016-04-25","CodigoEspecieAcao":"ON","CodigoClasseAcaoPreferencial":{},"ValorProventoPorAcao":"0.7200000000"},{"EventoOrigemProvento":"Assembléia Geral Ordinária","DataAprovacaoProvento":"2015-04-09","TipoProvento":"Juros sobre Capital Próprio","DataInicioPagamento":"2015-04-24","CodigoEspecieAcao":"ON","CodigoClasseAcaoPreferencial":{},"ValorProventoPorAcao":"1.2129700000"},{"EventoOrigemProvento":"Reunião do Conselho de Administração","DataAprovacaoProvento":"2015-07-27","TipoProvento":"Juros sobre Capital Próprio","DataInicioPagamento":"2015-08-14","CodigoEspecieAcao":"ON","CodigoClasseAcaoPreferencial":{},"ValorProventoPorAcao":"0.4980200000"}],"XmlCode":"53692"},{"ComposicaoCapitalSocial":{"QuantidadeAcaoOrdinariaCapitalIntegralizado":"113450000","QuantidadeAcaoPreferencialCapitalIntegralizado":"0","QuantidadeTotalAcaoCapitalIntegralizado":"113450000"},"Documento":{"CompanhiaAberta":{"NumeroSequencialRegistroCvm":"3630","CodigoTipoParticipante":"1","CodigoCvm":"020338","IndicadorSociedadeAnonimaAtiva":"true","NomeRazaoSocialCompanhiaAberta":"M DIAS BRANCO SA IND E COM DE ALIMENTOS","NumeroCnpjCompanhiaAberta":"07206816000115","CodigoCategoriaEmissor":"1","CodigoSituacaoRegistroCvm":"1","CodigoSituacaoCompanhiaAberta":"2","NumeroMesEncerramentoExercicioSocial":"0","NumeroAnoEncerramentoExercicioSocial":"0","TipoEmpresa":"0","DataRegistroCvm":"2006-10-11T00:00:00","DataInicioRazaoSocial":"0001-01-01T00:00:00","DataConstituicaoEmpresa":"1961-01-01T00:00:00","DataInicioSituacaoCompanhiaAberta":"2006-10-11T00:00:00","DataInicioSituacaoRegistroCvm":"2006-10-11T00:00:00","CodigoSetorAtividadeEmpresa":"1220","CodigoEspecieControleAcionario":"5","DataUltimaAlteracaoControleAcionario":"0001-01-01T00:00:00","DataRegistroAtualCategoriaEmissorCvm":"2010-01-01T00:00:00"},"DataReferenciaDocumento":"2014","CodigoEscalaQuantidade":"1"},"PagamentoProventoDinheiro":[],"XmlCode":"44390"},{"ComposicaoCapitalSocial":{"QuantidadeAcaoOrdinariaCapitalIntegralizado":"113450000","QuantidadeAcaoPreferencialCapitalIntegralizado":"0","QuantidadeTotalAcaoCapitalIntegralizado":"113450000"},"Documento":{"CompanhiaAberta":{"NumeroSequencialRegistroCvm":"3630","CodigoTipoParticipante":"1","CodigoCvm":"020338","IndicadorSociedadeAnonimaAtiva":"true","NomeRazaoSocialCompanhiaAberta":"M DIAS BRANCO SA IND E COM DE ALIMENTOS","NumeroCnpjCompanhiaAberta":"07206816000115","CodigoCategoriaEmissor":"1","CodigoSituacaoRegistroCvm":"1","CodigoSituacaoCompanhiaAberta":"2","NumeroMesEncerramentoExercicioSocial":"0","NumeroAnoEncerramentoExercicioSocial":"0","TipoEmpresa":"0","DataRegistroCvm":"2006-10-11T00:00:00","DataInicioRazaoSocial":"0001-01-01T00:00:00","DataConstituicaoEmpresa":"1961-01-01T00:00:00","DataInicioSituacaoCompanhiaAberta":"2006-10-11T00:00:00","DataInicioSituacaoRegistroCvm":"2006-10-11T00:00:00","CodigoSetorAtividadeEmpresa":"1220","CodigoEspecieControleAcionario":"5","DataUltimaAlteracaoControleAcionario":"0001-01-01T00:00:00","DataRegistroAtualCategoriaEmissorCvm":"2010-01-01T00:00:00"},"DataReferenciaDocumento":"2013","CodigoEscalaQuantidade":"1"},"PagamentoProventoDinheiro":[],"XmlCode":"35082"},{"ComposicaoCapitalSocial":{"QuantidadeAcaoOrdinariaCapitalIntegralizado":"113450000","QuantidadeAcaoPreferencialCapitalIntegralizado":"0","QuantidadeTotalAcaoCapitalIntegralizado":"113450000"},"Documento":{"CompanhiaAberta":{"NumeroSequencialRegistroCvm":"3630","CodigoTipoParticipante":"1","CodigoCvm":"020338","IndicadorSociedadeAnonimaAtiva":"true","NomeRazaoSocialCompanhiaAberta":"M DIAS BRANCO SA IND E COM DE ALIMENTOS","NumeroCnpjCompanhiaAberta":"07206816000115","CodigoCategoriaEmissor":"1","CodigoSituacaoRegistroCvm":"1","CodigoSituacaoCompanhiaAberta":"2","NumeroMesEncerramentoExercicioSocial":"0","NumeroAnoEncerramentoExercicioSocial":"0","TipoEmpresa":"0","DataRegistroCvm":"2006-10-11T00:00:00","DataInicioRazaoSocial":"0001-01-01T00:00:00","DataConstituicaoEmpresa":"1961-01-01T00:00:00","DataInicioSituacaoCompanhiaAberta":"2006-10-11T00:00:00","DataInicioSituacaoRegistroCvm":"2006-10-11T00:00:00","CodigoSetorAtividadeEmpresa":"1220","CodigoEspecieControleAcionario":"5","DataUltimaAlteracaoControleAcionario":"0001-01-01T00:00:00","DataRegistroAtualCategoriaEmissorCvm":"2010-01-01T00:00:00"},"DataReferenciaDocumento":"2012","CodigoEscalaQuantidade":"1"},"PagamentoProventoDinheiro":[],"XmlCode":"24638"},{"ComposicaoCapitalSocial":{"QuantidadeAcaoOrdinariaCapitalIntegralizado":"113450000","QuantidadeAcaoPreferencialCapitalIntegralizado":"0","QuantidadeTotalAcaoCapitalIntegralizado":"113450000"},"Documento":{"CompanhiaAberta":{"NumeroSequencialRegistroCvm":"3630","CodigoTipoParticipante":"1","CodigoCvm":"020338","IndicadorSociedadeAnonimaAtiva":"true","NomeRazaoSocialCompanhiaAberta":"M DIAS BRANCO SA IND E COM DE ALIMENTOS","NumeroCnpjCompanhiaAberta":"07206816000115","CodigoCategoriaEmissor":"1","CodigoSituacaoRegistroCvm":"1","CodigoSituacaoCompanhiaAberta":"2","NumeroMesEncerramentoExercicioSocial":"0","NumeroAnoEncerramentoExercicioSocial":"0","TipoEmpresa":"0","DataRegistroCvm":"2006-10-11T00:00:00","DataInicioRazaoSocial":"0001-01-01T00:00:00","DataConstituicaoEmpresa":"1961-01-01T00:00:00","DataInicioSituacaoCompanhiaAberta":"2006-10-11T00:00:00","DataInicioSituacaoRegistroCvm":"2006-10-11T00:00:00","CodigoSetorAtividadeEmpresa":"1220","CodigoEspecieControleAcionario":"5","DataUltimaAlteracaoControleAcionario":"0001-01-01T00:00:00","DataRegistroAtualCategoriaEmissorCvm":"2010-01-01T00:00:00"},"DataReferenciaDocumento":"2011","CodigoEscalaQuantidade":"1"},"PagamentoProventoDinheiro":[],"XmlCode":"14693"},{"ComposicaoCapitalSocial":{"QuantidadeAcaoOrdinariaCapitalIntegralizado":"113450","QuantidadeAcaoPreferencialCapitalIntegralizado":"0","QuantidadeTotalAcaoCapitalIntegralizado":"113450"},"Documento":{"CompanhiaAberta":{"NumeroSequencialRegistroCvm":"3630","CodigoTipoParticipante":"1","CodigoCvm":"020338","IndicadorSociedadeAnonimaAtiva":"true","NomeRazaoSocialCompanhiaAberta":"M DIAS BRANCO SA IND E COM DE ALIMENTOS","NumeroCnpjCompanhiaAberta":"07206816000115","CodigoCategoriaEmissor":"1","CodigoSituacaoRegistroCvm":"1","CodigoSituacaoCompanhiaAberta":"2","NumeroMesEncerramentoExercicioSocial":"0","NumeroAnoEncerramentoExercicioSocial":"0","TipoEmpresa":"0","DataRegistroCvm":"2006-10-11T00:00:00","DataInicioRazaoSocial":"0001-01-01T00:00:00","DataConstituicaoEmpresa":"1961-01-01T00:00:00","DataInicioSituacaoCompanhiaAberta":"2006-10-11T00:00:00","DataInicioSituacaoRegistroCvm":"2006-10-11T00:00:00","CodigoSetorAtividadeEmpresa":"1220","CodigoEspecieControleAcionario":"5","DataUltimaAlteracaoControleAcionario":"0001-01-01T00:00:00","DataRegistroAtualCategoriaEmissorCvm":"2010-01-01T00:00:00"},"DataReferenciaDocumento":"2010","CodigoEscalaQuantidade":"2"},"PagamentoProventoDinheiro":[],"XmlCode":"5050"}]}